{
  "Formula for Index": "5400",
  "Index": "5400",
  "Primary Source": [
    "129084651.json"
  ],
  "Secondary Source": [
    "716117817.json"
  ],
  "Current Source Question": [
    "670316988.json"
  ],
  "GridID/Source Question Name": [
    "SEASADD3_10"
  ],
  "conceptId": "258544530",
  "Current Question Text": "10-Seasonal Full Street name #2",
  "Variable Label": "Full Street name #2",
  "Variable Name": [
    "SrvLAW_SeaStrtName10_v1r0"
  ],
  "Connect Value for Select all that apply questions - Surveys Only": [
    "SEASTRTNAME10"
  ],
  "Variable Type": "Char",
  "Variable Length": "70",
  "Required": "No",
  "PII": "Yes",
  "Date added or modified": "3/3/22"
}