{
  "Primary Source": [
    "129084651.json"
  ],
  "Secondary Source": [
    "793330426.json"
  ],
  "Current Source Question": [
    "220055064.json"
  ],
  "V1 Source Question": [
    "Which COVID-19 vaccine shot did you get?"
  ],
  "GridID/Source Question Name": [
    "SrvCov_COV28SRC_v2r0"
  ],
  "conceptId": "224157985",
  "Current Question Text": "Which COVID-19 vaccine shot did you get?",
  "V1 Question Text": "Which COVID-19 vaccine shot did you get?  Question text diverged from source question",
  "Variable Label": "Vaccine Brand",
  "Variable Name": [
    "SrvCov_COV28_v2r0"
  ],
  "Variable Type": "Num",
  "Variable Length": "2",
  "Required": "No",
  "PII": "No",
  "Dictionary": "Biospecimen Survey",
  "State Attribute": "No",
  "Question Type": "Optional Multiple Choice with Text Box, Loops",
  "Formula for Index": [
    "9272",
    "9273",
    "9274",
    "9275",
    "9276",
    "9277",
    "9278"
  ],
  "Index": [
    "9272",
    "9273",
    "9274",
    "9275",
    "9276",
    "9277",
    "9278"
  ],
  "Current Format/Value": {
    "661871565.json": "0",
    "657978450.json": "1",
    "411943417.json": "2",
    "113838601.json": "3",
    "503154121.json": "4",
    "807835037.json": "55",
    "178420302.json": "77"
  },
  "Deprecated, New, or Revised": [
    "Revised",
    "New"
  ],
  "Date added or modified": [
    "7/12/2023; 10/1/2024",
    "6/15/23"
  ],
  "IMS Review Notes": [
    "Reverted variable name from _v1r1 to _v1r0.  Versioned source question and question text to unharmonize which requires a new concept ID for the question text.",
    "Denoted as New response"
  ]
}