{
  "Primary Source": [
    "129084651.json"
  ],
  "Secondary Source": [
    "726699695.json"
  ],
  "Current Source Question": [
    "308014437.json"
  ],
  "GridID/Source Question Name": [
    "RACEETH5"
  ],
  "conceptId": "412757551",
  "Current Question Text": "Ecuadorian",
  "Variable Label": "Ecuadorian",
  "Variable Name": [
    "SrvBOH_Ecuadorian_v1r0"
  ],
  "Connect Value for Select all that apply questions - Surveys Only": [
    "3"
  ],
  "Variable Type": "Num",
  "Variable Length": "1",
  "Required": "No",
  "PII": "No",
  "Notes": "Only display if RACEETH = Hispanic, Latino, or Spanish",
  "Question Type": "Optional Select All that Apply",
  "Formula for Index": [
    "2110",
    "2111"
  ],
  "Index": [
    "2110",
    "2111"
  ],
  "Current Format/Value": {
    "104430631.json": "0",
    "353358909.json": "1"
  }
}