{
  "conceptId": "469914719",
  "Current Question Text": "Child address- Please provide the cross streets of the intersection closest to this address:",
  "subcollections": [
    "952124199.json",
    "204186397.json",
    "469914719.json"
  ],
  "Formula for Index": "5721",
  "Index": "5721",
  "Primary Source": [
    "129084651.json"
  ],
  "Secondary Source": [
    "716117817.json"
  ],
  "Current Source Question": [
    "469914719.json"
  ],
  "GridID/Source Question Name": [
    "CHILDADD3"
  ],
  "Variable Label": "Do Not Know Childhood Cross",
  "Variable Name": [
    "SrvLAW_CHCrossDontKnow_v1r0"
  ],
  "Connect Value for Select all that apply questions - Surveys Only": [
    "CHILDADD3"
  ],
  "Variable Type": "Num",
  "Variable Length": "2",
  "Current Format/Value": {
    "178420302.json": "77"
  },
  "Required": "No",
  "PII": "No",
  "Date added or modified": "3/10/22"
}