{
  "Formula for Index": "3349",
  "Index": "3349",
  "Primary Source": [
    "129084651.json",
    "129084651.json",
    "129084651.json",
    "129084651.json",
    "129084651.json",
    "129084651.json",
    "129084651.json",
    "129084651.json",
    "129084651.json",
    "129084651.json",
    "129084651.json",
    "129084651.json",
    "129084651.json",
    "129084651.json"
  ],
  "Secondary Source": [
    "745268907.json",
    "745268907.json",
    "745268907.json",
    "745268907.json",
    "745268907.json",
    "745268907.json",
    "745268907.json",
    "745268907.json",
    "745268907.json",
    "745268907.json",
    "745268907.json",
    "745268907.json",
    "745268907.json",
    "745268907.json"
  ],
  "Current Source Question": [
    "596961796.json",
    "825189914.json",
    "753416375.json",
    "646042915.json",
    "799338907.json",
    "893965588.json",
    "438682764.json",
    "550092533.json",
    "901498441.json",
    "991622246.json",
    "273218182.json",
    "753610471.json",
    "803968511.json",
    "618427836.json"
  ],
  "GridID/Source Question Name": [
    "PAINREL3_1",
    "PAINREL3_2",
    "PAINREL3_3",
    "PAINREL3_4",
    "PAINREL3_5",
    "PAINREL3_6",
    "PAINREL3_7",
    "CHOLHTN3_1",
    "CHOLHTN3_2",
    "METFOR3_1",
    "INSULIN3_1",
    "ACIDSUP3_1",
    "ACIDSUP3_2",
    "ACIDSUP3_3"
  ],
  "conceptId": "101310722",
  "Current Question Text": "# Pills per day",
  "Variable Label": "Pills/Day Baby/Low-Dose Aspirin",
  "Variable Name": [
    "SrvMRE_LAspirinPill_v1r0",
    "SrvMRE_REAspirinPill_v1r0",
    "SrvMRE_IbuprofenPill_v1r0",
    "SrvMRE_AcetPill_v1r0",
    "SrvMRE_NaproxenPill_v1r0",
    "SrvMRE_CelebrexPill_v1r0",
    "SrvMRE_OpioidsPill_v1r0",
    "SrvMRE_StatinsPills_v1r0",
    "SrvMRE_AntiHypPills_v1r0",
    "SrvMRE_MetforminMg_v1r0",
    "SrvMRE_InsulinUnits_v1r0",
    "SrvMRE_PPPresPill_v1r0",
    "SrvMRE_PPOCPill_v1r0",
    "SrvMRE_H2RecBlocOCPill_v1r0"
  ],
  "Connect Value for Select all that apply questions - Surveys Only": [
    "PAINREL3_1A",
    "PAINREL3_2A",
    "PAINREL3_3A",
    "PAINREL3_4A",
    "PAINREL3_5A",
    "PAINREL3_6A",
    "PAINREL3_7A",
    "CHOLHTN3_1A",
    "CHOLHTN3_2A",
    "METFOR3_1A",
    "INSULIN3_1A",
    "ACIDSUP3_1A",
    "ACIDSUP3_2A",
    "ACIDSUP3_3A"
  ],
  "Variable Type": "Num",
  "Variable Length": "2",
  "Required": "No",
  "PII": "No",
  "Notes": "Only display if PAINREL1 = 0. Range check min = 1 and max = 99.",
  "Date added or modified": "8/24/23",
  "IMS Review Notes": "Added range check to Notes."
}