{
  "Primary Source": "https://github.com/episphere/conceptGithubActions/blob/master/jsons/506260723.json",
  "Secondary Source": "https://github.com/episphere/conceptGithubActions/blob/master/jsons/897962542.json",
  "conceptId": "126865182",
  "Question Text": "Healthcare provider",
  "Variable Label": "Site",
  "Variable Name": "RcrtES_Site_v1r0",
  "Variable Type": "Num",
  "Variable Length": "2",
  "Required": "Yes -  if there is not a valid token or PIN",
  "PII": "No",
  "Personal Note": "Confirm that this is only used with passive recruits",
  "Format/Value": {
    "889509156.json": "0",
    "270848954.json": "1",
    "419777405.json": "2",
    "452917455.json": "3",
    "558634301.json": "4",
    "456263788.json": "5",
    "556401486.json": "6",
    "183350544.json": "7",
    "769268265.json": "8",
    "681568390.json": "88"
  }
}