{
  "Formula for Index": "583",
  "Index": "583",
  "Primary Source": [
    "129084651.json"
  ],
  "Secondary Source": [
    "726699695.json"
  ],
  "conceptId": "205553981",
  "Current Question Text": "Autogenerated date/time stamp for Start of Module Background and Overall Health",
  "Variable Label": "Date/time Status of Start of Background and Overall Health",
  "Variable Name": [
    "SrvBOH_TmStart_v1r0"
  ],
  "Variable Type": "IS0",
  "Variable Length": "24",
  "Current Format/Value": "example: 2020-07-17T15:21:26.763Z",
  "Required": "Yes if SrvBOH_BaseStatus_v1r0 equals 1",
  "PII": "No",
  "Notes": "ISO to be converted to SAS format, populated when SrvBOH_BaseStatus_v1r0 is 1",
  "Dictionary": "Study Manager Data Dictionary",
  "State Attribute": "No",
  "Default Variable": "No",
  "Date added or modified": "6/10/21",
  "GCP Document/Table": "Participants Table Not nested (d_205553981)"
}