{
  "Primary Source": "Help Desk",
  "Secondary Source": "861315814.json",
  "Source Question": "685002411.json",
  "conceptId": "217367618",
  "Question Text": "Baseline specimen surveys",
  "Variable Label": "Baseline specimen surveys",
  "Variable Name": "HdRef_BlSpecSrv_v1r0",
  "Variable Type": "Num",
  "Variable Length": "1",
  "PII": "Yes",
  "Derivation Notes": "Set by help desk agent via dashboard",
  "State Attribute": "Withdrawal, Study Manager Data Dictionary",
  "Default Variable": "No",
  "Date added or modified": "Yes",
  "Quest_Src Question": "4/23/21",
  "Format/Value": {
    "104430631.json": "0",
    "353358909.json": "1"
  }
}