{
  "Primary Source": "Survey",
  "Secondary Source": "745268907.json",
  "Source Question": "305292465.json",
  "conceptId": "225191459",
  "Question Text": "anti-hypertensive medication/drugs used to treat hypertension (high blood pressure) days per month",
  "Variable Label": "anti-hypertensive medication/drugs used to treat hypertension (high blood pressure) days per month",
  "Variable Name": "SrvMRE_AntiHypertensMo_v1r0",
  "Connect Value for Select all that apply questions": "CHOLHTN2_2MO",
  "Variable Type": "Num",
  "Variable Length": "2",
  "Old Quest Value": "N/A",
  "Required": "No",
  "PII": "No",
  "Quest_Src Question": "CHOLHTN2_2"
}