{
  "Primary Source": "129084651.json",
  "Secondary Source": "898006288.json",
  "conceptId": "266847650",
  "Question Text": "Was your endometriosis confirmed by surgery?",
  "Variable Label": "Endometriosis surgery confirm",
  "Variable Name": "SrvBOH_EndoSurgery_v1r0",
  "Connect Value for Select all that apply questions": "ENDO2",
  "Variable Type": "Num",
  "Variable Length": "1",
  "Required": "No",
  "PII": "No",
  "Notes": "Only display if MHGROUP8= Endometriosis",
  "Old Quest Value": {
    "104430631.json": "2",
    "353358909.json": "1"
  }
}