{
  "Primary Source": "129084651.json",
  "Secondary Source": "898006288.json",
  "conceptId": "289664241",
  "Question Text": "Do you think of yourself as:",
  "Variable Label": "Gender",
  "Variable Name": "SrvBOH_Gender_v1r0",
  "Connect Value for Select all that apply questions": "GEN",
  "Variable Type": "Num",
  "Variable Length": "2",
  "Required": "No",
  "PII": "No",
  "Format/Value": [
    "690306025.json",
    "718514860.json",
    "870461040.json",
    "348203599.json",
    "215729851.json",
    "971664514.json",
    "455168483.json"
  ],
  "Old Quest Value": {
    "842579305.json": "1",
    "301468821.json": "2",
    "858887260.json": "3",
    "447470536.json": "4",
    "467419974.json": "5",
    "521203298.json": "6",
    "507664865.json": "99"
  },
  "Connect Value": {
    "301468821.json": "0",
    "842579305.json": "1",
    "858887260.json": "2",
    "447470536.json": "3",
    "467419974.json": "4",
    "627372907.json": "55",
    "934410958.json": "99"
  }
}