{
  "Primary Source": [
    "129084651.json"
  ],
  "Secondary Source": [
    "716117817.json"
  ],
  "Source Question": [
    "251048648.json"
  ],
  "GridID/Source Question Name": [
    "PREWORKT6"
  ],
  "conceptId": "368973683",
  "Question Text": "Bicycle commute from past work",
  "Variable Label": "Bicycle commute from past work",
  "Variable Name": [
    "SrvLAW_PreWorkBike4_v1r0"
  ],
  "Connect Value for Select all that apply questions - Surveys Only": [
    "5"
  ],
  "Variable Type": "Num",
  "Variable Length": "1",
  "Required": "No",
  "PII": "No",
  "Date added or modified": "44630",
  "Formula for Index": [
    "5887",
    "5888"
  ],
  "Index": [
    "5887",
    "5888"
  ],
  "Format/Value": {
    "104430631.json": "0",
    "353358909.json": "1"
  }
}