{
  "Formula for Index": "3510",
  "Index": "3510",
  "Primary Source": [
    "129084651.json"
  ],
  "Secondary Source": [
    "965707586.json"
  ],
  "conceptId": "399659169",
  "Question Text": "When you were a daily smoker, how many cigarettes did you smoke per day?",
  "Variable Label": "When daily user, number of cigarettes per day",
  "Variable Name": [
    "SrvSAS_DailyUseCigsDay_v1r0"
  ],
  "Connect Value for Select all that apply questions - Surveys Only": [
    "CIG9C"
  ],
  "Variable Type": "Num",
  "Variable Length": "2",
  "Format/Value": "N/A",
  "Required": "No",
  "PII": "No",
  "Date added or modified": "12/6/21"
}