{
  "Primary Source": "192505768.json",
  "Secondary Source": "883203566.json",
  "conceptId": "412947828",
  "Question Text": "Henry Ford Health System Race Ethnicity Combination",
  "Variable Label": "Henry Ford Health System Race Ethnicity Combination",
  "Variable Name": "RcrtSI_HFHSRE_v1r0",
  "Variable Type": "Num",
  "Variable Length": "2",
  "Required": "For Henry Ford HS",
  "PII": "No",
  "Dictionary": "Master Data Dictionary",
  "State Attribute": "No",
  "Default Variable": "No",
  "Derivation Notes": [
    "237561516.json",
    "770441471.json",
    "661135894.json",
    "398752944.json",
    "842144577.json",
    "603821095.json",
    "937758402.json",
    "121286752.json",
    "122287616.json",
    "912869944.json",
    "837570824.json",
    "387418774.json"
  ],
  "Format/Value": {
    "237561516.json": "0",
    "770441471.json": "1",
    "661135894.json": "2",
    "398752944.json": "3",
    "842144577.json": "4",
    "603821095.json": "5",
    "937758402.json": "6",
    "121286752.json": "7",
    "122287616.json": "8",
    "912869944.json": "9",
    "837570824.json": "10",
    "387418774.json": "77"
  }
}