{
  "Primary Source": "192505768.json",
  "Secondary Source": "883203566.json",
  "conceptId": "412947828",
  "Question Text": "Henry Ford Health System Race Ethnicity Combination",
  "Variable Label": "Henry Ford Health System Race Ethnicity Combination",
  "Variable Name": "RcrtSI_HFHSRE_v1r0",
  "Variable Type": "Num",
  "Variable Length": "2",
  "Required": "For Henry Ford HS",
  "PII": "No",
  "Dictionary": "Master Data Dictionary",
  "State Attribute": "No",
  "Default Variable": "No",
  "Derivation Notes": [
    "817575353.json",
    "267019866.json",
    "295290325.json",
    "378306807.json",
    "195262624.json",
    "541354190.json",
    "187684498.json",
    "748396823.json",
    "334987060.json",
    "243112835.json",
    "621202441.json",
    "658103896.json"
  ],
  "Format/Value": {
    "146377574.json": "0",
    "893222749.json": "1",
    "758835523.json": "2",
    "802930618.json": "3",
    "627968973.json": "4",
    "486528916.json": "5",
    "207709068.json": "6",
    "893146608.json": "7",
    "865678871.json": "8",
    "704660735.json": "9",
    "416419461.json": "10",
    "849902090.json": "77"
  }
}