{
  "Formula for Index": "4064",
  "Index": "4064",
  "Primary Source": [
    "129084651.json"
  ],
  "Secondary Source": [
    "965707586.json"
  ],
  "Source Question": [
    "755923078.json"
  ],
  "GridID/Source Question Name": [
    "TOMAR10"
  ],
  "conceptId": "459020144",
  "Question Text": "Why [do/did] you smoke a combination of marijuana with tobacco? Other: Please describe text box",
  "Variable Label": "Why [do/did] you smoke a combination of marijuana with tobacco - Descriptive",
  "Variable Name": [
    "SrvSAS_WhyTobMJOth_v1r0"
  ],
  "Connect Value for Select all that apply questions - Surveys Only": [
    "TOMAR10OTH"
  ],
  "Variable Type": "Char",
  "Required": "No",
  "PII": "No",
  "Date added or modified": "11/23/21"
}