{
  "Primary Source": [
    "129084651.json"
  ],
  "Secondary Source": [
    "506648060.json"
  ],
  "conceptId": "465287908",
  "Current Question Text": "How would you rate your experience donating samples? Please rate your experience on the amount of time donating samples",
  "Variable Label": "Biospecimen donation - amount of time",
  "Variable Name": [
    "SrvPES_BIOSAMP3A_v1r0"
  ],
  "Variable Type": "Num",
  "Variable Length": "1",
  "Required": "No",
  "PII": "No",
  "Dictionary": "Participant Experience Survey",
  "Date added or modified": "12/19/22",
  "Question Type": "Optional Multiple Choice",
  "Formula for Index": [
    "7401",
    "7402",
    "7403"
  ],
  "Index": [
    "7401",
    "7402",
    "7403"
  ],
  "Current Format/Value": {
    "777433416.json": "0",
    "589724105.json": "1",
    "576052130.json": "2"
  }
}