{
  "Formula for Index": "7254",
  "Index": "7254",
  "Primary Source": [
    "129084651.json"
  ],
  "Secondary Source": [
    "716117817.json"
  ],
  "Current Source Question": [
    "398762737.json"
  ],
  "Deprecated, New, or Revised": "Revised",
  "conceptId": "474541595",
  "Current Question Text": "1-Previous Full Street name #2",
  "Variable Label": "Full Street name #2",
  "Variable Name": [
    "SrvLAW_StrtName2_v1r0"
  ],
  "Variable Type": "Char",
  "Variable Length": "70",
  "Required": "No",
  "PII": "Yes",
  "IMS Review Notes": "Unharmonized source question and question text."
}