{
  "Formula for Index": "7221",
  "Index": "7221",
  "Primary Source": [
    "129084651.json"
  ],
  "Secondary Source": [
    "716117817.json"
  ],
  "Current Source Question": [
    "920576363.json"
  ],
  "Deprecated, New, or Revised": "Revised",
  "conceptId": "500100435",
  "Current Question Text": "Current Country - Follow-up",
  "Variable Label": "Country",
  "Variable Name": [
    "SrvLAW_CountryFollowUp_v1r0"
  ],
  "Variable Type": "Char",
  "Variable Length": "300",
  "Required": "No",
  "PII": "Yes",
  "IMS Review Notes": "Unharmonized source question and question text."
}