{"Primary Source":"544934974.json","Secondary Source":"382696437.json","conceptId":"518699521","Question Text":"Healthcare provider","Variable Label":"Site","Variable Name":"RcrtES_Site_v1r0","Variable Type":"Num","Variable Length":"2","Required":"Yes -  if there is not a valid token or PIN","PII":"No","Personal Note":"Confirm that this is only used with passive recruits","Source Question ":"784784912.json","Format/Value":{"059921422.json":"0","411868006.json":"1","940560351.json":"2","647108945.json":"3","783603131.json":"4","187754969.json":"5","261205851.json":"6","654969205.json":"7","293837211.json":"8","017037645.json":"88"}}