{
  "Formula for Index": "5259",
  "Index": "5259",
  "Primary Source": [
    "129084651.json"
  ],
  "Secondary Source": [
    "716117817.json"
  ],
  "conceptId": "537016132",
  "Current Question Text": "Please review the list below and tell us if it includes all of the addresses where you have spent a total of 24 months or more in the past 20 years. 10th Address:",
  "Variable Label": "Summary vacation homes",
  "Variable Name": [
    "SrvLAW_SeasAddSum_10_v1r0"
  ],
  "Connect Value for Select all that apply questions - Surveys Only": [
    "SEASADDSUM_10"
  ],
  "Variable Type": "Num",
  "Variable Length": "2",
  "Current Format/Value": {
    "472001636.json": "0"
  },
  "Required": "No",
  "PII": "No",
  "Question Type": "Optional Multiple Choice",
  "IMS Review Notes": "New addition"
}