{
  "Formula for Index": "246",
  "Primary Source": [
    "192505768.json"
  ],
  "Secondary Source": [
    "332759827.json"
  ],
  "conceptId": "544150384",
  "Current Question Text": "Birth Year",
  "Variable Label": "DOB Yr",
  "Variable Name": [
    "RcrtUP_YOB_v1r0"
  ],
  "Variable Type": "Year",
  "Variable Length": "4",
  "Current Format/Value": "yyyy",
  "PII": "Yes",
  "Notes": "Field will require a 4 digit response.",
  "Dictionary": "Recruitment Data Dictionary",
  "State Attribute": "No",
  "Default Variable": "No",
  "GCP Document/Table": "Participants Table Not nested (d_544150384)"
}