{
  "conceptId": "555481393",
  "Question Text": "Orientation - Do you think of yourself as:",
  "subcollections": [
    "555481393.json",
    "979809707.json"
  ],
  "Primary Source": [
    "129084651.json"
  ],
  "Secondary Source": [
    "726699695.json"
  ],
  "Source Question": [
    "555481393.json"
  ],
  "GridID/Source Question Name": [
    "SEXORIENT"
  ],
  "Variable Label": "Sexual orientation",
  "Variable Name": [
    "SrvBOH_SexOrient_v1r0"
  ],
  "Connect Value for Select all that apply questions - Surveys Only": [
    "SEXORIENT"
  ],
  "Variable Type": "Num",
  "Variable Length": "2",
  "Required": "No",
  "PII": "No",
  "Date added or modified": "9/14/21",
  "Question Type": "Optional Multiple Choice with Text Box (text in text box)",
  "Formula for Index": [
    "1083",
    "1084",
    "1085",
    "1086",
    "1087"
  ],
  "Index": [
    "1083",
    "1084",
    "1085",
    "1086",
    "1087"
  ],
  "Format/Value": {
    "271882746.json": "0",
    "903084185.json": "1",
    "999994434.json": "2",
    "807835037.json": "55",
    "746038746.json": "99"
  }
}