{
  "Formula for Index": "7033",
  "Index": "7033",
  "Primary Source": [
    "129084651.json"
  ],
  "Secondary Source": [
    "716117817.json"
  ],
  "Current Source Question": [
    "710127044.json"
  ],
  "GridID/Source Question Name": [
    "CURWORKPOSTPAN3_SRC"
  ],
  "Deprecated, New, or Revised": "New",
  "conceptId": "668270650",
  "Current Question Text": "Post Pan Employer Full street name #1",
  "Variable Label": "Cur Work Post Pan Cross St 1",
  "Variable Name": [
    "SrvLAW_WkPstPanCrossSt1_v1r0"
  ],
  "Connect Value for Select all that apply questions - Surveys Only": [
    "FULLST1_CURWORKPOSTPANST"
  ],
  "Variable Type": "Char",
  "Variable Length": "70",
  "Required": "No",
  "PII": "No",
  "Date added or modified": "10/8/2024; 12/31/2024",
  "IMS Review Notes": "Added new question. Updated Source Q and Current Question text to match Questionnaire and deleted CIDs. Unharmonized Sourse Q from Question text"
}