{
  "Formula for Index": "2682",
  "Index": "2682",
  "Primary Source": [
    "129084651.json"
  ],
  "Secondary Source": [
    "726699695.json"
  ],
  "Deprecated, New, or Revised": "Revised",
  "Date Deprecated, New, or Revised Variable Pushed to Prod": "2/1/24",
  "conceptId": "677262300",
  "Current Question Text": "How old were you when you reached your adult height? If you are not sure, please make your best guess.",
  "Variable Label": "Age Adult Height",
  "Variable Name": [
    "SrvBOH_AdultHt_v1r1"
  ],
  "Connect Value for Select all that apply questions - Surveys Only": [
    "ADUHEIGHT"
  ],
  "Variable Type": "Num",
  "Variable Length": "2",
  "Current Format/Value": "N/A",
  "Required": "No",
  "PII": "No",
  "Notes": "Range check (max previously was age): min=0 max=sum(isDefined(D_150344905,age),1)",
  "Date added or modified": "2/28/24",
  "Question Type": "Or (xor=) Question (either/or text boxes without radio button)",
  "IMS Review Notes": "Added prod push date"
}