{
  "Primary Source": "129084651.json",
  "Secondary Source": "965707586.json",
  "conceptId": "685401343",
  "Question Text": "When was the last time you used chewing tobacco, snus, snuff, or dip?",
  "Variable Label": "Last used chewing tobacco, snus, snuff, or dip",
  "Variable Name": "SrvSAS_LastUsedCT_v1r0",
  "Connect Value for Select all that apply questions": "CHEW5",
  "Variable Type": "Num",
  "Variable Length": "2",
  "Required": "No",
  "PII": "No",
  "Old Quest Value": {
    "317567178.json": "1",
    "484055234.json": "2",
    "802197176.json": "3"
  },
  "Connect Value": {
    "317567178.json": "0",
    "484055234.json": "1",
    "802197176.json": "2"
  }
}