{
  "Formula for Index": "7740",
  "Index": "7740",
  "Primary Source": [
    "129084651.json"
  ],
  "Secondary Source": [
    "716117817.json"
  ],
  "Current Source Question": [
    "279093430.json"
  ],
  "Deprecated, New, or Revised": "Revised",
  "conceptId": "715370929",
  "Current Question Text": "2-Seasonal City",
  "Variable Label": "City",
  "Variable Name": [
    "SrvLAW_SeaCity2_v1r0"
  ],
  "Variable Type": "Char",
  "Variable Length": "45",
  "Required": "No",
  "PII": "Yes",
  "IMS Review Notes": "Added SOURCE to Source Question and _SRC to the Grid ID for consistency, but did not change concept IDs."
}