{
  "Primary Source": [
    "237817859.json"
  ],
  "Secondary Source": [
    "635994596.json"
  ],
  "conceptId": "747006172",
  "Question Text": "Withdraw consent",
  "Variable Label": "Withdraw consent",
  "Variable Name": [
    "HdWd_WdConsent_v1r0"
  ],
  "Variable Type": "Num",
  "Variable Length": "1",
  "Required": "Yes",
  "PII": "No",
  "Notes": "Set by help desk agent via dashboard. Withdraw Consent also triggers Revoke HIPAA",
  "Dictionary": "Withdrawal, Study Manager Data Dictionary",
  "State Attribute": "No",
  "Default Variable": "Yes",
  "Date added or modified": "4/22/21",
  "Formula for Index": [
    "590",
    "591",
    "592"
  ],
  "Index": [
    "590",
    "591",
    "592"
  ],
  "Format/Value": {
    "104430631.json": "0",
    "353358909.json": "1"
  }
}