{
  "Primary Source": "129084651.json",
  "Secondary Source": "745268907.json",
  "conceptId": "756521698",
  "Question Text": "How often do you stop breathing during your sleep?",
  "Variable Label": "Often stop breathing",
  "Variable Name": "SrvMRE_StopBreathing_v1r0",
  "Connect Value for Select all that apply questions": "SNORING5",
  "Variable Type": "Num",
  "Variable Length": "2",
  "Required": "No",
  "PII": "No",
  "Old Quest Value": {
    "718687985.json": "1",
    "471294296.json": "2",
    "198347104.json": "3",
    "632512449.json": "4",
    "520089841.json": "5",
    "648960871.json": "6",
    "495230752.json": "77"
  },
  "Connect Value": {
    "718687985.json": "0",
    "471294296.json": "1",
    "198347104.json": "2",
    "632512449.json": "3",
    "520089841.json": "4",
    "648960871.json": "5",
    "920765381.json": "77"
  }
}