{
  "Formula for Index": "265",
  "Primary Source": [
    "192505768.json"
  ],
  "Secondary Source": [
    "705748897.json"
  ],
  "conceptId": "756862764",
  "Current Question Text": "Firebase authentication first and last name",
  "Variable Label": "Acct Name",
  "Variable Name": [
    "displayName"
  ],
  "Variable Type": "Char",
  "Variable Length": "50",
  "Current Format/Value": "N/A",
  "Required": "Yes",
  "PII": "Yes",
  "Dictionary": "Recruitment Data Dictionary",
  "State Attribute": "No",
  "Default Variable": "No",
  "GCP Document/Table": "Participants Table Not nested (d_756862764)"
}