{
  "Primary Source": [
    "129084651.json"
  ],
  "Secondary Source": [
    "726699695.json"
  ],
  "Source Question": [
    "797626610.json"
  ],
  "conceptId": "774928994",
  "Question Text": "None of these White categories fully describe me. Please describe [text box]",
  "Variable Label": "None of these fully describe me. Please describe [text box]",
  "Variable Name": [
    "SrvBOH_NoneDescribeRE8_v1r0"
  ],
  "Connect Value for Select all that apply questions": [
    "RACEETH8_TB"
  ],
  "Variable Type": "Char",
  "Variable Length": "300",
  "Connect Value": "N/A",
  "Required": "No",
  "PII": "No",
  "Notes": "Only display if RACEETH = White",
  "Date added or modified": "9/14/21",
  "Question Type": "Optional Select All that Apply",
  "Quest_Src Question": [
    "RACEETH8"
  ]
}