{
  "conceptId": "790436165",
  "Current Question Text": "Age first used cigarettes on a regular basis",
  "subcollections": [
    "408696162.json",
    "790436165.json"
  ],
  "Formula for Index": "3591",
  "Index": "3591",
  "Primary Source": [
    "129084651.json"
  ],
  "Secondary Source": [
    "965707586.json"
  ],
  "Source Question": [
    "790436165.json"
  ],
  "GridID/Source Question Name": [
    "CIG3"
  ],
  "Variable Label": "Age first used cigarettes on a regular basis, Never smoked",
  "Variable Name": [
    "SrvSAS_NeverSmokedReg_v1r0"
  ],
  "Connect Value for Select all that apply questions - Surveys Only": [
    "CIG3"
  ],
  "Variable Type": "Num",
  "Variable Length": "2",
  "Current Format/Value": {
    "648960871.json": "44"
  },
  "Date added or modified": "11/23/21"
}