{
  "Formula for Index": "5000",
  "Index": "5000",
  "Primary Source": [
    "129084651.json"
  ],
  "Secondary Source": [
    "716117817.json"
  ],
  "Source Question": [
    "376408004.json"
  ],
  "GridID/Source Question Name - Surveys Only": [
    "SEASADD1_1"
  ],
  "conceptId": "812433386",
  "Question Text": "1-Seasonal Zip code",
  "Variable Label": "Zip code",
  "Variable Name": [
    "SrvLAW_SeaZip_v1r0"
  ],
  "Connect Value for Select all that apply questions - Surveys Only": [
    "SEAZIP"
  ],
  "Variable Type": "Num",
  "Variable Length": "5",
  "Required": "No",
  "PII": "Yes",
  "Date added or modified": "2/3/22"
}