{
  "Primary Source": "129084651.json",
  "Secondary Source": "898006288.json",
  "conceptId": "820324171",
  "Question Text": "When you were about 10 years old, compared to average, would you describe yourself as…",
  "Variable Label": "10 year old weight",
  "Variable Name": "SrvBOH_10YrWeight_v1r0",
  "Variable Type": "AVEWEIGHT",
  "Variable Length": "Num",
  "PII": "No",
  "Old Quest Value": [
    "549652033.json",
    "650188281.json",
    "444957913.json"
  ],
  "Required": {
    "305743567.json": "0",
    "198069473.json": "1",
    "654018491.json": "2"
  }
}