{
  "Formula for Index": "1457",
  "Index": "1457",
  "Primary Source": [
    "129084651.json"
  ],
  "Secondary Source": [
    "601305072.json"
  ],
  "Deprecated, New, or Revised": "New",
  "Date Deprecated, New, or Revised Variable Pushed to Prod": "8/28/24",
  "conceptId": "870643066",
  "Current Question Text": "Autogenerated date/time stamp for Start of PROMIS survey",
  "Variable Label": "D/T PROMIS Surv Start",
  "Variable Name": [
    "SrvQOL_3moTmStart_v1r0"
  ],
  "Variable Type": "ISO",
  "Variable Length": "24",
  "Current Format/Value": "example: 2020-07-17T15:21:26.763Z",
  "Required": "Yes if SrvQOL_3moStatus_v1r0 equals 1",
  "PII": "No",
  "Notes": "ISO to be converted to SAS format",
  "Dictionary": "PROMIS Survey",
  "State Attribute": "No",
  "Default Variable": "No",
  "Date added or modified": "2/8/24",
  "GCP Document/Table": "Participants Table"
}