{
  "Formula for Index": "313",
  "Primary Source": [
    "192505768.json"
  ],
  "Secondary Source": [
    "332759827.json"
  ],
  "Deprecated, New, or Revised": "New",
  "Date Deprecated, New, or Revised Variable Pushed to Prod": "1/29/24",
  "conceptId": "876546260",
  "Current Question Text": "Place of Birth- City",
  "Variable Label": "Birth City",
  "Variable Name": [
    "RcrtUP_PoBCity_v1r0"
  ],
  "Variable Type": "Char",
  "Variable Length": "45",
  "Current Format/Value": "N/A",
  "Required": "No",
  "PII": "Yes",
  "Notes": "Will not be nested",
  "Dictionary": "Recruitment Data Dictionary",
  "State Attribute": "No",
  "Default Variable": "No",
  "Date added or modified": "11/14/24"
}