{
  "Primary Source": [
    "129084651.json"
  ],
  "Secondary Source": [
    "716117817.json"
  ],
  "Current Source Question": [
    "635467479.json"
  ],
  "Deprecated, New, or Revised": "Revised",
  "conceptId": "892894242",
  "Current Question Text": "Motorcycle commute to work",
  "Variable Label": "Motorcycle commute to current work",
  "Variable Name": [
    "SrvLAW_CurWorkMoto_v1r0"
  ],
  "Connect Value for Select all that apply questions - Surveys Only": [
    "TRUE"
  ],
  "Variable Type": "Num",
  "Variable Length": "1",
  "Required": "No",
  "PII": "No",
  "IMS Review Notes": "Updated tense in source question to reflect past job rather than current job.",
  "Formula for Index": [
    "8519",
    "8520"
  ],
  "Index": [
    "8519",
    "8520"
  ],
  "Current Format/Value": {
    "104430631.json": "0",
    "353358909.json": "1"
  }
}