{
  "Primary Source": "129084651.json",
  "Secondary Source": "745268907.json",
  "conceptId": "910856756",
  "Question Text": "Overall, how was your sleep on a usual night sleep during the past 4 weeks?",
  "Variable Label": "How was sleep last 4 weeks",
  "Variable Name": "SrvMRE_SleepLast4Wk_v1r0",
  "Connect Value for Select all that apply questions": "SLHABIT2",
  "Variable Type": "Num",
  "Variable Length": "2",
  "Required": "No",
  "PII": "No",
  "Old Quest Value": {
    "462478011.json": "1",
    "303095574.json": "2",
    "838403733.json": "3",
    "522143286.json": "4",
    "621370621.json": "5"
  }
}