{
  "conceptId": "973670172",
  "Current Question Text": "Urine Tube 1",
  "subcollections": [
    "593843561.json",
    "825582494.json",
    "883732523.json",
    "472864016.json",
    "550088682.json",
    "690540566.json",
    "956345366.json",
    "757246707.json",
    "728366619.json",
    "453343022.json",
    "762124027.json",
    "338286049.json",
    "536710547.json",
    "678857215.json",
    "926457119.json",
    "810960823.json",
    "777486216.json",
    "684617815.json",
    "283900611.json",
    "982885431.json",
    "313097539.json"
  ],
  "Formula for Index": "970",
  "Index": "970",
  "Primary Source": [
    "819848608.json"
  ],
  "Secondary Source": [
    "360770860.json"
  ],
  "Variable Label": "Ur",
  "Variable Name": [
    "BioCol_0006_v1r0"
  ],
  "Variable Type": "N/A",
  "Variable Length": "N/A",
  "Current Format/Value": "N/A",
  "Required": "Yes if marked as Collected",
  "PII": "No",
  "Dictionary": "Biospecimen Clinical, Biospecimen Research, Biospecimen Shipping",
  "State Attribute": "No",
  "Default Variable": "No",
  "GCP Document/Table": "Biospecimen Table Nested structure: d_973670172_d_248868659_Deviation OR d_973670172_OtherTubeDetails"
}