{
  "Primary Source": "Recruitment",
  "Secondary Source": "332759827.json",
  "conceptId": "983278853",
  "Question Text": "Can we leave voicemail at this number?",
  "Variable Label": "Other voicemail",
  "Variable Name": "RcrtUP_OtherVM_v1r0",
  "Variable Type": "Num",
  "Variable Length": "1",
  "PII": "No",
  "State Attribute": "Recruitment Data Dictionary, Biospecimen Research",
  "Default Variable": "No",
  "Date added or modified": "No",
  "Format/Value": {
    "104430631.json": "0",
    "353358909.json": "1"
  }
}